{
  "$schema": "https://railway.app/railway.schema.json",
  "build": {
    "builder": "dockerfile",
    "dockerfilePath": "scanner-worker.Dockerfile"
  },
  "deploy": {
    "startCommand": "python worker.py",
    "healthcheckPath": "/",
    "healthcheckTimeout": 30,
    "restartPolicyType": "always",
    "replicas": 2
  },
  "environments": {
    "production": {
      "variables": {
        "REDIS_URL": "${{Redis.REDIS_URL}}",
        "RAILWAY_REPLICA_ID": "${{RAILWAY_REPLICA_ID}}"
      }
    }
  }
}