[
  {
    "rule": "API4",
    "title": "Lack of Rate Limiting",
    "severity": "Low",
    "score": 3.0,
    "endpoint": "/users/v1/{username}",
    "method": "GET",
    "description": "Burst of requests did not trigger 429 nor expose rate limit headers; RL likely missing.",
    "evidence": {
      "statuses": [
        404,
        404,
        404,
        404,
        404,
        404,
        404,
        404,
        404,
        404
      ],
      "headers_sample": [
        {},
        {},
        {}
      ]
    }
  },
  {
    "rule": "API7",
    "title": "Security Misconfiguration",
    "severity": "Medium",
    "score": 4.8,
    "endpoint": "/",
    "method": "GET",
    "description": "Server base URL uses plaintext HTTP (no TLS).",
    "evidence": {
      "server_base": "http://localhost:5002"
    }
  }
]